seedoku/__init__.py
seedoku/__main__.py
seedoku/sudoku.py
seedoku/trackers/anchors.csv
seedoku/trackers/hand_tracker.py
seedoku/trackers/non_maximum_suppression.py
seedoku/trackers/palm_detection_without_custom_op.tflite
seedoku-1.1.dist-info/LICENSE
seedoku-1.1.dist-info/METADATA
seedoku-1.1.dist-info/WHEEL
seedoku-1.1.dist-info/entry_points.txt
seedoku-1.1.dist-info/top_level.txt
seedoku-1.1.dist-info/RECORD
