Metadata-Version: 2.1
Name: seedoku
Version: 1.1
Summary: Play Sudoku with your Hands on a Real Time Camera Feed
Home-page: https://github.com/aashish2000/seedoku
Author: Aashish
Author-email: aash.ananth@gmail.com
License: GPL
Platform: UNKNOWN
Classifier: License :: OSI Approved :: GNU General Public License v3 (GPLv3)
Classifier: Programming Language :: Python :: 3
Classifier: Programming Language :: Python :: 3.6
Requires-Dist: tensorflow (==2.3.0)
Requires-Dist: opencv-python (==4.4.0.42)
Requires-Dist: imutils (==0.5.3)
